{
  "updatedAt": "2026-07-08T21:56:56.695Z",
  "groups": {
    "machineHeadlines": [
      {
        "time": "02:04",
        "title": "部品不足で生産ラインを止めないために--設備保全クラウド「ミロクルカルテ」、モバイルで完結する部品棚卸し機能α版をリリース",
        "source": "山陽新聞",
        "url": "https://news.google.com/rss/articles/CBMiUkFVX3lxTE0xZHhmZUhvWi16YTRtLWRBUkZCaU5VOWItRlg1eHNDclRyOXNCUXZSajdlQ05keE5QWXQ1X09WeThvbHhPbDM2Z1hmc1ZkSVBEY2c?oc=5",
        "publishedAt": "2026-07-08T17:04:27.000Z"
      },
      {
        "time": "13:30",
        "title": "ソディックが新プラットフォームを提供、機械の設備監視と遠隔サポートを統合：工作機械",
        "source": "MONOist",
        "url": "https://news.google.com/rss/articles/CBMib0FVX3lxTE1Xd1lZYzZldDlpMEJybENrZVJGNHQtVS1KZFNPT3A0MnpWR3BxZ01ncGRRQlRRNkRENTZ6UWJSTmt1NGJpLVlvU2d1NXdiWVJ5Q2lWaDhGZ084ci1jeEE0QnNiS2VQREZlZ0tkUnRjaw?oc=5",
        "publishedAt": "2026-07-08T04:30:00.000Z"
      },
      {
        "time": "10:30",
        "title": "【設備保全DX】メンテナンス・レジリエンス2026 に次世代設備保全クラウド「M2X」ブースを出展",
        "source": "PR TIMES",
        "url": "https://news.google.com/rss/articles/CBMiakFVX3lxTE1CcW9GMGVqWFByZWdIa0FFVXpqdlhsSEZ1VHg0bTBiSXl1cGNfNzNWRVZiWWRTY1IzSHFYbTlBbnl2Z0RCQkFIQTlsb3dOWEpxUzhkTVhWRUFSUktBMDAyQm9aV2xRYzRxcnc?oc=5",
        "publishedAt": "2026-07-08T01:30:38.000Z"
      },
      {
        "time": "05:10",
        "title": "工作機械や小型プリンターのスター精密、NotionとNotion AIを国内全社ナレッジ基盤として導入",
        "source": "rbbtoday.com",
        "url": "https://news.google.com/rss/articles/CBMieEFVX3lxTE9Mdmk4SkNsY29WV3ItYmdfcWw0eGJ0U1lPd2dheF9Vd3JqTUthUzR4aVJJSUN1MmxYSlo4aFBZNEZudjdtaU1HSVFDSVdLcktsX3FjbHJWRlVWM0dfR001R2w0Yy14S1BBSmhUZGxBRjZZNnRlZTJacQ?oc=5",
        "publishedAt": "2026-07-08T20:10:02.000Z"
      },
      {
        "time": "02:33",
        "title": "日本の工作機械、中国の地方都市に敗れ始める―中国メディア",
        "source": "Record China",
        "url": "https://news.google.com/rss/articles/CBMiXEFVX3lxTE40TmY3dVVCS3NJMGFDenhvLWxPNEROMjdscnl0S25xMFZxRHhHQ1BRYTVTRVBrdmt3X3VwNllkUmtwWE9rSDJDRGZRZFJWblZ1dmZvUWVUYm9GSXV5?oc=5",
        "publishedAt": "2026-07-08T17:33:57.000Z"
      },
      {
        "time": "15:01",
        "title": "DMG森精機、長時間稼働AMRの新型発売",
        "source": "LOGISTICS TODAY",
        "url": "https://news.google.com/rss/articles/CBMiSEFVX3lxTE5vcVo4WE45YzJSZTNMT0kwa1RUSmo5cmdfOC14bGN3SFVOYVRWT0hPRnRQa0g4LWJySFN2OXlETUNMcThZMldNSw?oc=5",
        "publishedAt": "2026-07-08T06:01:07.000Z"
      },
      {
        "time": "13:00",
        "title": "位置エンコーダチップの世界市場（2026年～2032年）、市場規模（アナログ信号出力タイプ、デジタル信号出力タイプ）・分析レポートを発表",
        "source": "newscast.jp",
        "url": "https://news.google.com/rss/articles/CBMiT0FVX3lxTE5fcE1VQVNRS0k5Tzgtd09GV0ozWnZ3SUFFajBIR2VkOXRULWMtcVVCempRc01tenZNLUZ6cHptUzdmZTlPYTdSY09JdEIxTEU?oc=5",
        "publishedAt": "2026-07-08T04:00:00.000Z"
      },
      {
        "time": "05:01",
        "title": "挑む・モノづくりヒトづくり／小松電気化学工業社長・西章洋氏",
        "source": "日刊工業新聞",
        "url": "https://news.google.com/rss/articles/CBMiW0FVX3lxTE5oYWRtZHJyN0E5am9ZcUNIbmJCWmpQMFoyeWNNaVdjUVdVQjVzLXVLSW1WeGFfNEFMblVVWGNnX2p1U2EzTTdOX0FjcDFHQTJneGYtcGJtVlJ1LU0?oc=5",
        "publishedAt": "2026-07-08T20:01:43.000Z"
      }
    ],
    "worldHeadlines": [
      {
        "time": "06:20",
        "title": "米軍 イランへの新たな攻撃実施",
        "source": "Yahoo!ニュース",
        "url": "https://news.yahoo.co.jp/pickup/6587240?source=rss",
        "publishedAt": "2026-07-08T21:20:25.000Z"
      },
      {
        "time": "23:50",
        "title": "米 ウにパトリオット生産を容認へ",
        "source": "Yahoo!ニュース",
        "url": "https://news.yahoo.co.jp/pickup/6587235?source=rss",
        "publishedAt": "2026-07-08T14:50:23.000Z"
      },
      {
        "time": "20:18",
        "title": "スペインと貿易停止 米大統領指示",
        "source": "Yahoo!ニュース",
        "url": "https://news.yahoo.co.jp/pickup/6587215?source=rss",
        "publishedAt": "2026-07-08T11:18:05.000Z"
      },
      {
        "time": "23:37",
        "title": "米大統領 イランと日本言い間違え",
        "source": "Yahoo!ニュース",
        "url": "https://news.yahoo.co.jp/pickup/6587233?source=rss",
        "publishedAt": "2026-07-08T14:37:14.000Z"
      },
      {
        "time": "16:07",
        "title": "ベネズエラ地震 掘り出せぬ遺体も",
        "source": "Yahoo!ニュース",
        "url": "https://news.yahoo.co.jp/pickup/6587172?source=rss",
        "publishedAt": "2026-07-08T07:07:59.000Z"
      },
      {
        "time": "11:34",
        "title": "モナコ爆弾事件 容疑者がウで死亡",
        "source": "Yahoo!ニュース",
        "url": "https://news.yahoo.co.jp/pickup/6587137?source=rss",
        "publishedAt": "2026-07-08T02:34:09.000Z"
      }
    ],
    "economyHeadlines": [
      {
        "time": "23:26",
        "title": "全東信が破産 2万店超に未入金か",
        "source": "Yahoo!ニュース",
        "url": "https://news.yahoo.co.jp/pickup/6587232?source=rss",
        "publishedAt": "2026-07-08T14:26:25.000Z"
      },
      {
        "time": "17:30",
        "title": "全東信破産 20年前から粉飾決算か",
        "source": "Yahoo!ニュース",
        "url": "https://news.yahoo.co.jp/pickup/6587189?source=rss",
        "publishedAt": "2026-07-08T08:30:48.000Z"
      },
      {
        "time": "18:17",
        "title": "ノーリツが下請法違反 公取委勧告",
        "source": "Yahoo!ニュース",
        "url": "https://news.yahoo.co.jp/pickup/6587199?source=rss",
        "publishedAt": "2026-07-08T09:17:40.000Z"
      },
      {
        "time": "22:44",
        "title": "暑さで勝手に仕事中断 法的には",
        "source": "Yahoo!ニュース",
        "url": "https://news.yahoo.co.jp/pickup/6587228?source=rss",
        "publishedAt": "2026-07-08T13:44:43.000Z"
      },
      {
        "time": "17:16",
        "title": "夫の転勤で妻は転職 家族にも負担",
        "source": "Yahoo!ニュース",
        "url": "https://news.yahoo.co.jp/pickup/6587179?source=rss",
        "publishedAt": "2026-07-08T08:16:01.000Z"
      },
      {
        "time": "17:18",
        "title": "焼肉店窮地 ロピアが新たな競合?",
        "source": "Yahoo!ニュース",
        "url": "https://news.yahoo.co.jp/pickup/6587188?source=rss",
        "publishedAt": "2026-07-08T08:18:19.000Z"
      }
    ],
    "localHeadlines": [
      {
        "time": "06:11",
        "title": "住宅で70代死亡 殺人疑い息子逮捕",
        "source": "Yahoo!ニュース",
        "url": "https://news.yahoo.co.jp/pickup/6587239?source=rss",
        "publishedAt": "2026-07-08T21:11:21.000Z"
      },
      {
        "time": "17:54",
        "title": "事故で乳児重体 救出者「生きろ」",
        "source": "Yahoo!ニュース",
        "url": "https://news.yahoo.co.jp/pickup/6587194?source=rss",
        "publishedAt": "2026-07-08T08:54:54.000Z"
      },
      {
        "time": "16:19",
        "title": "ガンホー元本部長 背任疑いで逮捕",
        "source": "Yahoo!ニュース",
        "url": "https://news.yahoo.co.jp/pickup/6587177?source=rss",
        "publishedAt": "2026-07-08T07:19:28.000Z"
      },
      {
        "time": "22:45",
        "title": "唇を縫い付けた疑い 共犯もいたか",
        "source": "Yahoo!ニュース",
        "url": "https://news.yahoo.co.jp/pickup/6587226?source=rss",
        "publishedAt": "2026-07-08T13:45:37.000Z"
      },
      {
        "time": "22:19",
        "title": "検事 元容疑者の女性と不適切交際",
        "source": "Yahoo!ニュース",
        "url": "https://news.yahoo.co.jp/pickup/6587225?source=rss",
        "publishedAt": "2026-07-08T13:19:10.000Z"
      },
      {
        "time": "01:02",
        "title": "「カツアゲ」告発の県議 金銭受領",
        "source": "Yahoo!ニュース",
        "url": "https://news.yahoo.co.jp/pickup/6587237?source=rss",
        "publishedAt": "2026-07-08T16:02:30.000Z"
      }
    ],
    "subsidyHeadlines": [
      {
        "time": "5/15",
        "title": "2026年度 事業者向け創エネ・蓄エネ・省エネ設備導入等補助金交付事業について",
        "source": "福山市",
        "url": "https://www.city.fukuyama.hiroshima.jp/site/kankyo/394078.html"
      },
      {
        "time": "3/2",
        "title": "グリーンな企業賃上げ環境整備支援事業補助金について",
        "source": "福山市",
        "url": "https://www.city.fukuyama.hiroshima.jp/soshiki/sangyou/391140.html"
      },
      {
        "time": "4/3",
        "title": "広島県 中小企業省エネ設備等導入支援補助金について",
        "source": "広島県",
        "url": "https://www.pref.hiroshima.lg.jp/site/eco/shoenehojokin-r8.html"
      },
      {
        "time": "確認",
        "title": "中小企業省力化投資補助金の公募・採択情報を確認",
        "source": "中小機構",
        "url": "https://seisansei.smrj.go.jp/subsidy_info/laborsaving_subsidy.html"
      },
      {
        "time": "16:00",
        "title": "2026年 補助金まとめ！中小企業向け主要補助金のポイント解説",
        "source": "補助金ポータル",
        "url": "https://news.google.com/rss/articles/CBMiakFVX3lxTE9Idm5vYjJtajVIYjhheTZVVTVQTXRXMndVNkRmWnVEZnZyNVRRV3ZncXZhREsxNXBqYXFZSlZmNHhLeHhkbUNRcXljRlJNWVh2ZmZrSXlsVVJsdGI5RGtBdmoxUGx1YlozMUE?oc=5",
        "publishedAt": "2026-07-01T07:00:00.000Z"
      },
      {
        "time": "16:00",
        "title": "食洗機設置の設置で使える！省エネ住宅補助金",
        "source": "補助金ポータル",
        "url": "https://news.google.com/rss/articles/CBMiZEFVX3lxTE8wb3R6alFKeVRpMkVWVGpiMjRhdGVkZFhZZXRBTl8yeU5xTDlwMDQwelhkQ3hFSnNaMEszMjRYMl9VYjAxUi1xVzRzSEkwTWkxLXZhbndUWkpGUUg4aXY4V0VPSDQ?oc=5",
        "publishedAt": "2026-06-30T07:00:00.000Z"
      }
    ]
  }
}
