{
  "updatedAt": "2026-07-20T03:12:31.724Z",
  "groups": {
    "machineHeadlines": [
      {
        "time": "10:54",
        "title": "日米合意1年 関税の負担依然重く",
        "source": "Yahoo!ニュース",
        "url": "https://news.yahoo.co.jp/pickup/6588606?source=rss",
        "publishedAt": "2026-07-20T01:54:28.000Z"
      },
      {
        "time": "16:12",
        "title": "ニチレイの障害 物流復旧へ正念場",
        "source": "Yahoo!ニュース",
        "url": "https://news.yahoo.co.jp/pickup/6588516?source=rss",
        "publishedAt": "2026-07-19T07:12:22.000Z"
      },
      {
        "time": "19:06",
        "title": "飲食店倒産増 個人店どう生き残る",
        "source": "Yahoo!ニュース",
        "url": "https://news.yahoo.co.jp/pickup/6588540?source=rss",
        "publishedAt": "2026-07-19T10:06:16.000Z"
      },
      {
        "time": "09:32",
        "title": "マンジャロの違法転売 取り巻く闇",
        "source": "Yahoo!ニュース",
        "url": "https://news.yahoo.co.jp/pickup/6588598?source=rss",
        "publishedAt": "2026-07-20T00:32:41.000Z"
      },
      {
        "time": "09:49",
        "title": "契約書や許可なし ヤミ小作の実態",
        "source": "Yahoo!ニュース",
        "url": "https://news.yahoo.co.jp/pickup/6588600?source=rss",
        "publishedAt": "2026-07-20T00:49:28.000Z"
      },
      {
        "time": "14:41",
        "title": "冷やし甘酒が特産品に 海外輸出も",
        "source": "Yahoo!ニュース",
        "url": "https://news.yahoo.co.jp/pickup/6588506?source=rss",
        "publishedAt": "2026-07-19T05:41:17.000Z"
      },
      {
        "time": "22:41",
        "title": "換気扇24h使う?浴室売る2社見解",
        "source": "Yahoo!ニュース",
        "url": "https://news.yahoo.co.jp/pickup/6588568?source=rss",
        "publishedAt": "2026-07-19T13:41:08.000Z"
      },
      {
        "time": "16:30",
        "title": "解説滑らか 87歳の男性バスガイド",
        "source": "Yahoo!ニュース",
        "url": "https://news.yahoo.co.jp/pickup/6588519?source=rss",
        "publishedAt": "2026-07-19T07:30:49.000Z"
      }
    ],
    "worldHeadlines": [
      {
        "time": "09:06",
        "title": "米国の対イラン攻撃 範囲が拡大",
        "source": "Yahoo!ニュース",
        "url": "https://news.yahoo.co.jp/pickup/6588597?source=rss",
        "publishedAt": "2026-07-20T00:06:20.000Z"
      },
      {
        "time": "22:01",
        "title": "日比海洋交渉入り合意 中国猛反発",
        "source": "Yahoo!ニュース",
        "url": "https://news.yahoo.co.jp/pickup/6588562?source=rss",
        "publishedAt": "2026-07-19T13:01:32.000Z"
      },
      {
        "time": "15:23",
        "title": "NY市長 イスラエル首相拘束検討",
        "source": "Yahoo!ニュース",
        "url": "https://news.yahoo.co.jp/pickup/6588509?source=rss",
        "publishedAt": "2026-07-19T06:23:54.000Z"
      },
      {
        "time": "12:34",
        "title": "世界一律の10%代替関税 失効へ",
        "source": "Yahoo!ニュース",
        "url": "https://news.yahoo.co.jp/pickup/6588491?source=rss",
        "publishedAt": "2026-07-19T03:34:46.000Z"
      },
      {
        "time": "18:04",
        "title": "露 キーウに弾道ミサイル40発以上",
        "source": "Yahoo!ニュース",
        "url": "https://news.yahoo.co.jp/pickup/6588533?source=rss",
        "publishedAt": "2026-07-19T09:04:47.000Z"
      },
      {
        "time": "19:26",
        "title": "日ウ企業間の技術協力 露が批判",
        "source": "Yahoo!ニュース",
        "url": "https://news.yahoo.co.jp/pickup/6588544?source=rss",
        "publishedAt": "2026-07-19T10:26:29.000Z"
      }
    ],
    "economyHeadlines": [
      {
        "time": "10:54",
        "title": "日米合意1年 関税の負担依然重く",
        "source": "Yahoo!ニュース",
        "url": "https://news.yahoo.co.jp/pickup/6588606?source=rss",
        "publishedAt": "2026-07-20T01:54:28.000Z"
      },
      {
        "time": "16:12",
        "title": "ニチレイの障害 物流復旧へ正念場",
        "source": "Yahoo!ニュース",
        "url": "https://news.yahoo.co.jp/pickup/6588516?source=rss",
        "publishedAt": "2026-07-19T07:12:22.000Z"
      },
      {
        "time": "19:06",
        "title": "飲食店倒産増 個人店どう生き残る",
        "source": "Yahoo!ニュース",
        "url": "https://news.yahoo.co.jp/pickup/6588540?source=rss",
        "publishedAt": "2026-07-19T10:06:16.000Z"
      },
      {
        "time": "09:32",
        "title": "マンジャロの違法転売 取り巻く闇",
        "source": "Yahoo!ニュース",
        "url": "https://news.yahoo.co.jp/pickup/6588598?source=rss",
        "publishedAt": "2026-07-20T00:32:41.000Z"
      },
      {
        "time": "09:49",
        "title": "契約書や許可なし ヤミ小作の実態",
        "source": "Yahoo!ニュース",
        "url": "https://news.yahoo.co.jp/pickup/6588600?source=rss",
        "publishedAt": "2026-07-20T00:49:28.000Z"
      },
      {
        "time": "14:41",
        "title": "冷やし甘酒が特産品に 海外輸出も",
        "source": "Yahoo!ニュース",
        "url": "https://news.yahoo.co.jp/pickup/6588506?source=rss",
        "publishedAt": "2026-07-19T05:41:17.000Z"
      }
    ],
    "localHeadlines": [
      {
        "time": "11:07",
        "title": "関東甲信と東海が梅雨明け 気象庁",
        "source": "Yahoo!ニュース",
        "url": "https://news.yahoo.co.jp/pickup/6588607?source=rss",
        "publishedAt": "2026-07-20T02:07:45.000Z"
      },
      {
        "time": "07:16",
        "title": "正面衝突で2人死亡1人重体 逆走か",
        "source": "Yahoo!ニュース",
        "url": "https://news.yahoo.co.jp/pickup/6588578?source=rss",
        "publishedAt": "2026-07-19T22:16:27.000Z"
      },
      {
        "time": "08:25",
        "title": "3歳男児ひかれ死亡 1人で道路渡る",
        "source": "Yahoo!ニュース",
        "url": "https://news.yahoo.co.jp/pickup/6588587?source=rss",
        "publishedAt": "2026-07-19T23:25:49.000Z"
      },
      {
        "time": "23:41",
        "title": "老舗酒造会社「越後鶴亀」全焼か",
        "source": "Yahoo!ニュース",
        "url": "https://news.yahoo.co.jp/pickup/6588573?source=rss",
        "publishedAt": "2026-07-19T14:41:18.000Z"
      },
      {
        "time": "20:48",
        "title": "スポーツカーとSUV衝突 2人死亡",
        "source": "Yahoo!ニュース",
        "url": "https://news.yahoo.co.jp/pickup/6588552?source=rss",
        "publishedAt": "2026-07-19T11:48:54.000Z"
      },
      {
        "time": "22:46",
        "title": "クマ3頭と遭遇し襲われる 搬送",
        "source": "Yahoo!ニュース",
        "url": "https://news.yahoo.co.jp/pickup/6588569?source=rss",
        "publishedAt": "2026-07-19T13:46:20.000Z"
      }
    ],
    "subsidyHeadlines": [
      {
        "time": "5/15",
        "title": "2026年度 事業者向け創エネ・蓄エネ・省エネ設備導入等補助金交付事業について",
        "source": "福山市",
        "url": "https://www.city.fukuyama.hiroshima.jp/site/kankyo/394078.html"
      },
      {
        "time": "3/2",
        "title": "グリーンな企業賃上げ環境整備支援事業補助金について",
        "source": "福山市",
        "url": "https://www.city.fukuyama.hiroshima.jp/soshiki/sangyou/391140.html"
      },
      {
        "time": "4/3",
        "title": "広島県 中小企業省エネ設備等導入支援補助金について",
        "source": "広島県",
        "url": "https://www.pref.hiroshima.lg.jp/site/eco/shoenehojokin-r8.html"
      },
      {
        "time": "確認",
        "title": "中小企業省力化投資補助金の公募・採択情報を確認",
        "source": "中小機構",
        "url": "https://seisansei.smrj.go.jp/subsidy_info/laborsaving_subsidy.html"
      }
    ]
  }
}
